super_stream_tools/__init__.py
super_stream_tools/cli.py
super_stream_tools/tools.py
super_stream_tools/stream_library/__init__.py
super_stream_tools/stream_library/async_downloads.py
super_stream_tools/stream_library/async_subprocess.py
super_stream_tools-0.2.4.data/scripts/stream-tools
super_stream_tools-0.2.4.dist-info/LICENSE
super_stream_tools-0.2.4.dist-info/METADATA
super_stream_tools-0.2.4.dist-info/WHEEL
super_stream_tools-0.2.4.dist-info/top_level.txt
super_stream_tools-0.2.4.dist-info/RECORD
