Metadata-Version: 2.1
Name: super-stream-tools
Version: 0.2.4
Summary: A tool to interact with streaming URLs easily
Home-page: https://github.com/korigamik/media-tools
Author: KorigamiK
Author-email: korigamik@gmail.com
License: MIT
Keywords: python,video,stream,video stream,encode,ffmpeg
Platform: UNKNOWN
Classifier: Development Status :: 1 - Planning
Classifier: Intended Audience :: Science/Research
Classifier: Operating System :: POSIX :: Linux
Classifier: Programming Language :: Python :: 3.10
Classifier: Intended Audience :: Developers
Classifier: Operating System :: Unix
Classifier: Operating System :: MacOS :: MacOS X
Classifier: Operating System :: Microsoft :: Windows
Requires-Python: >=3.9
License-File: LICENSE
Requires-Dist: asyncio
Requires-Dist: aiohttp
Requires-Dist: aiofiles
